{
  "user": {
    "gender": "Mr",
    "name": "Hovhannes",
    "email": "Hovhannesmkrtchyan40@gmail.com",
    "password": "password123",
    "dayOfBirth": "5",
    "monthOfBirth": "9",
    "yearOfBirth": "1993",
    "newsletter": true,
    "specialOffers": true,
    "firstName": "Hovhannes",
    "lastName": "Mkrtchyan",
    "company": "Example Corp",
    "address": "123 Main St",
    "country": "USA",
    "state": "California",
    "city": "Los Angeles",
    "zipcode": "2015",
    "mobileNumber": "1234567890"
  },
  "card": {
    "name": "Test User",
    "number": "1234567891011121",
    "cvc": "123",
    "expiryMonth": "12",
    "expiryYear": "2024"
  }
}
